pikuli/File.py
pikuli/Match.py
pikuli/Pattern.py
pikuli/Screen.py
pikuli/_SettingsClass.py
pikuli/__init__.py
pikuli/_exceptions.py
pikuli/_functions.py
pikuli/_helpers.py
pikuli/cv_element.py
pikuli/geom/__init__.py
pikuli/geom/location.py
pikuli/geom/region.py
pikuli/geom/vector.py
pikuli/hwnd/__init__.py
pikuli/hwnd/hwnd_element.py
pikuli/input/__init__.py
pikuli/input/constants.py
pikuli/input/helper_types.py
pikuli/input/input_emulator.py
pikuli/input/keys.py
pikuli/input/linux_evdev/__init__.py
pikuli/input/linux_evdev/dumpkeys_f.txt
pikuli/input/linux_evdev/dumpkeys_l.txt
pikuli/input/linux_evdev/input_emulator.py
pikuli/input/linux_gtk3/__init__.py
pikuli/input/linux_gtk3/clipboard.py
pikuli/input/linux_gtk3/input_emulator.py
pikuli/input/linux_gtk3/xmodmap_pk.txt
pikuli/input/linux_x11/__init__.py
pikuli/input/linux_x11/clipboard.py
pikuli/input/linux_x11/input_emulator.py
pikuli/input/platform_init.py
pikuli/input/windows/__init__.py
pikuli/input/windows/clipboard.py
pikuli/input/windows/input_emulator.py
pikuli/logger.py
pikuli/mouse_cursor.py
pikuli/uia/__init__.py
pikuli/uia/adapter/__init__.py
pikuli/uia/adapter/adapter.py
pikuli/uia/adapter/adapter_base.py
pikuli/uia/adapter/dotnet/__init__.py
pikuli/uia/adapter/dotnet/adapter.py
pikuli/uia/adapter/dotnet/automation_element.py
pikuli/uia/adapter/dotnet/condition.py
pikuli/uia/adapter/dotnet/pattern_factory.py
pikuli/uia/adapter/dotnet/tree_walker.py
pikuli/uia/adapter/dotnet/value_converters.py
pikuli/uia/adapter/helper_types.py
pikuli/uia/adapter/identifer_names.py
pikuli/uia/adapter/oleacc_h.py
pikuli/uia/adapter/pattern_description.py
pikuli/uia/adapter/patterns_plain_description.py
pikuli/uia/adapter/platform_init.py
pikuli/uia/adapter/property_value_converter.py
pikuli/uia/adapter/property_value_types.py
pikuli/uia/adapter/sdk_enums.py
pikuli/uia/adapter/win_native/__init__.py
pikuli/uia/adapter/win_native/adapter.py
pikuli/uia/adapter/win_native/automation_element.py
pikuli-0.0.2.dist-info/LICENSE
pikuli-0.0.2.dist-info/WHEEL
pikuli-0.0.2.dist-info/METADATA
pikuli-0.0.2.dist-info/RECORD
